file_service_client/__init__.py
file_service_client/file_service_client.py
file_service_client/file_store_client.py
file_service_client/models.py
file_service_client/utils.py
file_service_client-2.2.3.dist-info/LICENSE.txt
file_service_client-2.2.3.dist-info/METADATA
file_service_client-2.2.3.dist-info/WHEEL
file_service_client-2.2.3.dist-info/top_level.txt
file_service_client-2.2.3.dist-info/RECORD
